distance/__init__.py
distance/distance.py
jeekdistance-0.0.2.dist-info/METADATA
jeekdistance-0.0.2.dist-info/WHEEL
jeekdistance-0.0.2.dist-info/top_level.txt
jeekdistance-0.0.2.dist-info/RECORD
