Metadata-Version: 2.1
Name: jeekdistance
Version: 0.0.2
Summary: A small example package
Home-page: UNKNOWN
Author: jeek
Author-email: 785501952@qq.com
License: UNKNOWN
Platform: UNKNOWN
Classifier: Programming Language :: Python :: 3
Classifier: License :: OSI Approved :: MIT License
Classifier: Operating System :: OS Independent
Requires-Dist: argparse
